README.rst
setup.py
bin_parser.egg-info/PKG-INFO
bin_parser.egg-info/SOURCES.txt
bin_parser.egg-info/dependency_links.txt
bin_parser.egg-info/entry_points.txt
bin_parser.egg-info/requires.txt
bin_parser.egg-info/top_level.txt
extras/__init__.py
extras/compare_yaml.py
extras/make_skeleton.py
python/__init__.py
python/bin_parser.py
python/cli.py
python/deprecated.py
python/functions.py