Metadata-Version: 1.0
Name: bin-parser
Version: 1.0.1
Summary: General binary file parser
Home-page: http://bin-parser.readthedocs.io/en/latest/
Author: Jeroen F.J. Laros
Author-email: J.F.J.Laros@lumc.nl
License: MIT License
Platform: any
